[
  {
    "file": "SN6_Train_AOI_11_Rotterdam_PS-RGB_20190804111224_20190804111453_tile_8679.tif",
    "label": "storagetank",
    "score": 0.97,
    "bbox": {
      "min_lon": 4.347554387208981,
      "min_lat": 51.88971907396971,
      "max_lon": 4.347871962061352,
      "max_lat": 51.889895005196806
    },
    "center": {
      "lon": 4.347713174336948,
      "lat": 51.88980703963268
    }
  },
  {
    "file": "SN6_Train_AOI_11_Rotterdam_PS-RGB_20190804111224_20190804111453_tile_8679.tif",
    "label": "storagetank",
    "score": 0.96,
    "bbox": {
      "min_lon": 4.342323883433367,
      "min_lat": 51.890371793037986,
      "max_lon": 4.342726060583423,
      "max_lat": 51.890619709725534
    },
    "center": {
      "lon": 4.342524971476566,
      "lat": 51.890495751481545
    }
  },
  {
    "file": "SN6_Train_AOI_11_Rotterdam_PS-RGB_20190804111224_20190804111453_tile_8679.tif",
    "label": "storagetank",
    "score": 0.96,
    "bbox": {
      "min_lon": 4.342006115521413,
      "min_lat": 51.89025240739665,
      "max_lon": 4.3423911304171225,
      "max_lat": 51.8904833786618
    },
    "center": {
      "lon": 4.342198622494808,
      "lat": 51.8903678931155
    }
  },
  {
    "file": "SN6_Train_AOI_11_Rotterdam_PS-RGB_20190804111224_20190804111453_tile_8679.tif",
    "label": "storagetank",
    "score": 0.96,
    "bbox": {
      "min_lon": 4.341985184467317,
      "min_lat": 51.89049152998012,
      "max_lon": 4.342358012898678,
      "max_lat": 51.890717873204956
    },
    "center": {
      "lon": 4.3421715982328095,
      "lat": 51.89060470167553
    }
  },
  {
    "file": "SN6_Train_AOI_11_Rotterdam_PS-RGB_20190804111224_20190804111453_tile_8679.tif",
    "label": "storagetank",
    "score": 0.95,
    "bbox": {
      "min_lon": 4.341573322067772,
      "min_lat": 51.890337866811684,
      "max_lon": 4.341823163944137,
      "max_lat": 51.89048493246502
    },
    "center": {
      "lon": 4.341698242809882,
      "lat": 51.89041139967323
    }
  },
  {
    "file": "SN6_Train_AOI_11_Rotterdam_PS-RGB_20190804111224_20190804111453_tile_8679.tif",
    "label": "storagetank",
    "score": 0.95,
    "bbox": {
      "min_lon": 4.341806110863387,
      "min_lat": 51.89040098126074,
      "max_lon": 4.342044410830484,
      "max_lat": 51.890544717264646
    },
    "center": {
      "lon": 4.341925260664195,
      "lat": 51.89047284929614
    }
  },
  {
    "file": "SN6_Train_AOI_11_Rotterdam_PS-RGB_20190804111224_20190804111453_tile_8679.tif",
    "label": "storagetank",
    "score": 0.95,
    "bbox": {
      "min_lon": 4.341534346912471,
      "min_lat": 51.8905450272867,
      "max_lon": 4.341717939122488,
      "max_lat": 51.89066064730322
    },
    "center": {
      "lon": 4.34162614290428,
      "lat": 51.89060283731674
    }
  },
  {
    "file": "SN6_Train_AOI_11_Rotterdam_PS-RGB_20190804111224_20190804111453_tile_8679.tif",
    "label": "storagetank",
    "score": 0.94,
    "bbox": {
      "min_lon": 4.3416411110340345,
      "min_lat": 51.88807075213247,
      "max_lon": 4.342087274820889,
      "max_lat": 51.88832252907171
    },
    "center": {
      "lon": 4.341864192327875,
      "lat": 51.88819664070367
    }
  },
  {
    "file": "SN6_Train_AOI_11_Rotterdam_PS-RGB_20190804111224_20190804111453_tile_8679.tif",
    "label": "storagetank",
    "score": 0.92,
    "bbox": {
      "min_lon": 4.347815680846473,
      "min_lat": 51.889960302753735,
      "max_lon": 4.348047680185323,
      "max_lat": 51.89010839775402
    },
    "center": {
      "lon": 4.347931680332738,
      "lat": 51.89003435028963
    }
  },
  {
    "file": "SN6_Train_AOI_11_Rotterdam_PS-RGB_20190804111224_20190804111453_tile_8679.tif",
    "label": "storagetank",
    "score": 0.92,
    "bbox": {
      "min_lon": 4.347493726263173,
      "min_lat": 51.88991725574925,
      "max_lon": 4.347778793855718,
      "max_lat": 51.89008381031189
    },
    "center": {
      "lon": 4.347636259806115,
      "lat": 51.890000533075245
    }
  },
  {
    "file": "SN6_Train_AOI_11_Rotterdam_PS-RGB_20190804111224_20190804111453_tile_8679.tif",
    "label": "storagetank",
    "score": 0.91,
    "bbox": {
      "min_lon": 4.341676275668005,
      "min_lat": 51.89013103655567,
      "max_lon": 4.342062487091575,
      "max_lat": 51.890363554436256
    },
    "center": {
      "lon": 4.3418693809006825,
      "lat": 51.89024729558344
    }
  },
  {
    "file": "SN6_Train_AOI_11_Rotterdam_PS-RGB_20190804111224_20190804111453_tile_8679.tif",
    "label": "storagetank",
    "score": 0.91,
    "bbox": {
      "min_lon": 4.347866086798838,
      "min_lat": 51.889759946344654,
      "max_lon": 4.34804165050658,
      "max_lat": 51.88990625254687
    },
    "center": {
      "lon": 4.34795386851641,
      "lat": 51.88983309948177
    }
  },
  {
    "file": "SN6_Train_AOI_11_Rotterdam_PS-RGB_20190804111224_20190804111453_tile_8679.tif",
    "label": "storagetank",
    "score": 0.9,
    "bbox": {
      "min_lon": 4.3416444667303224,
      "min_lat": 51.89064829211351,
      "max_lon": 4.341828013357887,
      "max_lat": 51.89076375189815
    },
    "center": {
      "lon": 4.341736239931089,
      "lat": 51.89070602202754
    }
  },
  {
    "file": "SN6_Train_AOI_11_Rotterdam_PS-RGB_20190804111224_20190804111453_tile_8679.tif",
    "label": "storagetank",
    "score": 0.89,
    "bbox": {
      "min_lon": 4.3419119991436705,
      "min_lat": 51.88790497537024,
      "max_lon": 4.342414120505897,
      "max_lat": 51.888025164663276
    },
    "center": {
      "lon": 4.342163059505669,
      "lat": 51.88796507003523
    }
  },
  {
    "file": "SN6_Train_AOI_11_Rotterdam_PS-RGB_20190804111224_20190804111453_tile_8679.tif",
    "label": "storagetank",
    "score": 0.89,
    "bbox": {
      "min_lon": 4.341764374922105,
      "min_lat": 51.890749093337405,
      "max_lon": 4.341983942458714,
      "max_lat": 51.89087100833105
    },
    "center": {
      "lon": 4.341874158547503,
      "lat": 51.890810050857986
    }
  },
  {
    "file": "SN6_Train_AOI_11_Rotterdam_PS-RGB_20190804111224_20190804111453_tile_8679.tif",
    "label": "storagetank",
    "score": 0.88,
    "bbox": {
      "min_lon": 4.34152916930775,
      "min_lat": 51.89003645819238,
      "max_lon": 4.34179928006275,
      "max_lat": 51.890190983270394
    },
    "center": {
      "lon": 4.341664224462472,
      "lat": 51.89011372076974
    }
  },
  {
    "file": "SN6_Train_AOI_11_Rotterdam_PS-RGB_20190804111224_20190804111453_tile_8679.tif",
    "label": "storagetank",
    "score": 0.88,
    "bbox": {
      "min_lon": 4.3415268152067945,
      "min_lat": 51.89072394957419,
      "max_lon": 4.341663343057692,
      "max_lat": 51.890830984716494
    },
    "center": {
      "lon": 4.34159507905458,
      "lat": 51.8907774671645
    }
  },
  {
    "file": "SN6_Train_AOI_11_Rotterdam_PS-RGB_20190804111224_20190804111453_tile_8679.tif",
    "label": "storagetank",
    "score": 0.77,
    "bbox": {
      "min_lon": 4.341593128673442,
      "min_lat": 51.88940763268778,
      "max_lon": 4.341817908401394,
      "max_lat": 51.889542434134384
    },
    "center": {
      "lon": 4.341705518375754,
      "lat": 51.88947503344047
    }
  },
  {
    "file": "SN6_Train_AOI_11_Rotterdam_PS-RGB_20190804111224_20190804111453_tile_8679.tif",
    "label": "storagetank",
    "score": 0.77,
    "bbox": {
      "min_lon": 4.341817612091743,
      "min_lat": 51.88950088857846,
      "max_lon": 4.342107603588243,
      "max_lat": 51.88967659025492
    },
    "center": {
      "lon": 4.341962607568178,
      "lat": 51.889588739466696
    }
  },
  {
    "file": "SN6_Train_AOI_11_Rotterdam_PS-RGB_20190804111224_20190804111453_tile_8679.tif",
    "label": "storagetank",
    "score": 0.71,
    "bbox": {
      "min_lon": 4.341517154986595,
      "min_lat": 51.89019306139077,
      "max_lon": 4.34169041712965,
      "max_lat": 51.89031293791543
    },
    "center": {
      "lon": 4.341603785947496,
      "lat": 51.89025299967679
    }
  },
  {
    "file": "SN6_Train_AOI_11_Rotterdam_PS-RGB_20190804111224_20190804111453_tile_8679.tif",
    "label": "storagetank",
    "score": 0.58,
    "bbox": {
      "min_lon": 4.347927454553833,
      "min_lat": 51.890625343199716,
      "max_lon": 4.348069195524366,
      "max_lat": 51.890826323214156
    },
    "center": {
      "lon": 4.347998324890907,
      "lat": 51.8907258332777
    }
  },
  {
    "file": "SN6_Train_AOI_11_Rotterdam_PS-RGB_20190804111224_20190804111453_tile_8679.tif",
    "label": "storagetank",
    "score": 0.42,
    "bbox": {
      "min_lon": 4.341518185705949,
      "min_lat": 51.890434596122,
      "max_lon": 4.341617955520202,
      "max_lat": 51.89055191202325
    },
    "center": {
      "lon": 4.34156807055163,
      "lat": 51.890493254096455
    }
  },
  {
    "file": "SN6_Train_AOI_11_Rotterdam_PS-RGB_20190804111224_20190804111453_tile_8681.tif",
    "label": "storagetank",
    "score": 0.93,
    "bbox": {
      "min_lon": 4.34906038372022,
      "min_lat": 51.89009578913037,
      "max_lon": 4.349349823640653,
      "max_lat": 51.89026770289943
    },
    "center": {
      "lon": 4.349205103414987,
      "lat": 51.89018174606258
    }
  },
  {
    "file": "SN6_Train_AOI_11_Rotterdam_PS-RGB_20190804111224_20190804111453_tile_8681.tif",
    "label": "storagetank",
    "score": 0.93,
    "bbox": {
      "min_lon": 4.348451419485422,
      "min_lat": 51.89002549399603,
      "max_lon": 4.348729301740923,
      "max_lat": 51.89019013222187
    },
    "center": {
      "lon": 4.348590360369101,
      "lat": 51.89010781315267
    }
  },
  {
    "file": "SN6_Train_AOI_11_Rotterdam_PS-RGB_20190804111224_20190804111453_tile_8681.tif",
    "label": "storagetank",
    "score": 0.92,
    "bbox": {
      "min_lon": 4.348202746382105,
      "min_lat": 51.889791872405354,
      "max_lon": 4.348483204975842,
      "max_lat": 51.88996113437251
    },
    "center": {
      "lon": 4.348342975425761,
      "lat": 51.88987650343526
    }
  },
  {
    "file": "SN6_Train_AOI_11_Rotterdam_PS-RGB_20190804111224_20190804111453_tile_8681.tif",
    "label": "storagetank",
    "score": 0.92,
    "bbox": {
      "min_lon": 4.348519366602082,
      "min_lat": 51.889827533515685,
      "max_lon": 4.348802917166346,
      "max_lat": 51.88999289592185
    },
    "center": {
      "lon": 4.348661141634035,
      "lat": 51.88991021476278
    }
  },
  {
    "file": "SN6_Train_AOI_11_Rotterdam_PS-RGB_20190804111224_20190804111453_tile_8681.tif",
    "label": "storagetank",
    "score": 0.91,
    "bbox": {
      "min_lon": 4.349137097491347,
      "min_lat": 51.88989266612376,
      "max_lon": 4.349426766541639,
      "max_lat": 51.89006175979329
    },
    "center": {
      "lon": 4.349281931755162,
      "lat": 51.88997721300455
    }
  },
  {
    "file": "SN6_Train_AOI_11_Rotterdam_PS-RGB_20190804111224_20190804111453_tile_8681.tif",
    "label": "storagetank",
    "score": 0.91,
    "bbox": {
      "min_lon": 4.34882694127312,
      "min_lat": 51.88986271482968,
      "max_lon": 4.349109524329615,
      "max_lat": 51.8900279825493
    },
    "center": {
      "lon": 4.348968232552195,
      "lat": 51.88994534873346
    }
  },
  {
    "file": "SN6_Train_AOI_11_Rotterdam_PS-RGB_20190804111224_20190804111453_tile_8681.tif",
    "label": "storagetank",
    "score": 0.9,
    "bbox": {
      "min_lon": 4.348761404015261,
      "min_lat": 51.89006307765201,
      "max_lon": 4.349031023602876,
      "max_lat": 51.89022240022358
    },
    "center": {
      "lon": 4.348896213579897,
      "lat": 51.890142738978724
    }
  },
  {
    "file": "SN6_Train_AOI_11_Rotterdam_PS-RGB_20190804111224_20190804111453_tile_8681.tif",
    "label": "storagetank",
    "score": 0.89,
    "bbox": {
      "min_lon": 4.3481425115197485,
      "min_lat": 51.889988934912914,
      "max_lon": 4.348411190642058,
      "max_lat": 51.890148633284696
    },
    "center": {
      "lon": 4.348276850852,
      "lat": 51.89006878413996
    }
  },
  {
    "file": "SN6_Train_AOI_11_Rotterdam_PS-RGB_20190804111224_20190804111453_tile_8681.tif",
    "label": "storagetank",
    "score": 0.86,
    "bbox": {
      "min_lon": 4.348055092509497,
      "min_lat": 51.890348590404784,
      "max_lon": 4.348353824451923,
      "max_lat": 51.89053424998699
    },
    "center": {
      "lon": 4.348204458184953,
      "lat": 51.890441420251875
    }
  },
  {
    "file": "SN6_Train_AOI_11_Rotterdam_PS-RGB_20190804111224_20190804111453_tile_8681.tif",
    "label": "storagetank",
    "score": 0.81,
    "bbox": {
      "min_lon": 4.3480378508891215,
      "min_lat": 51.88977404386946,
      "max_lon": 4.3481926859136975,
      "max_lat": 51.88990295374652
    },
    "center": {
      "lon": 4.348115268295494,
      "lat": 51.88983849883592
    }
  },
  {
    "file": "SN6_Train_AOI_11_Rotterdam_PS-RGB_20190804111224_20190804111453_tile_8681.tif",
    "label": "vehicle",
    "score": 0.76,
    "bbox": {
      "min_lon": 4.352526896667459,
      "min_lat": 51.88908301290448,
      "max_lon": 4.352783282307256,
      "max_lat": 51.88915291372972
    },
    "center": {
      "lon": 4.352655089392296,
      "lat": 51.889117963323656
    }
  },
  {
    "file": "SN6_Train_AOI_11_Rotterdam_PS-RGB_20190804111224_20190804111453_tile_8681.tif",
    "label": "storagetank",
    "score": 0.74,
    "bbox": {
      "min_lon": 4.352417192348852,
      "min_lat": 51.89022558515745,
      "max_lon": 4.352638028239004,
      "max_lat": 51.890355497819215
    },
    "center": {
      "lon": 4.352527610140882,
      "lat": 51.89029054151553
    }
  },
  {
    "file": "SN6_Train_AOI_11_Rotterdam_PS-RGB_20190804111224_20190804111453_tile_8681.tif",
    "label": "storagetank",
    "score": 0.72,
    "bbox": {
      "min_lon": 4.348063484694169,
      "min_lat": 51.89062966915481,
      "max_lon": 4.348306614475635,
      "max_lat": 51.890816179482755
    },
    "center": {
      "lon": 4.348185049343848,
      "lat": 51.890722924376774
    }
  },
  {
    "file": "SN6_Train_AOI_11_Rotterdam_PS-RGB_20190804111224_20190804111453_tile_8681.tif",
    "label": "vehicle",
    "score": 0.69,
    "bbox": {
      "min_lon": 4.353514150879661,
      "min_lat": 51.887947958574905,
      "max_lon": 4.353623199071141,
      "max_lat": 51.88810031519767
    },
    "center": {
      "lon": 4.353568674888936,
      "lat": 51.88802413692691
    }
  },
  {
    "file": "SN6_Train_AOI_11_Rotterdam_PS-RGB_20190804111224_20190804111453_tile_8681.tif",
    "label": "storagetank",
    "score": 0.67,
    "bbox": {
      "min_lon": 4.3523981607733635,
      "min_lat": 51.89035967656923,
      "max_lon": 4.352587016922084,
      "max_lat": 51.89046962539484
    },
    "center": {
      "lon": 4.352492588736939,
      "lat": 51.890414651001464
    }
  },
  {
    "file": "SN6_Train_AOI_11_Rotterdam_PS-RGB_20190804111224_20190804111453_tile_8681.tif",
    "label": "storagetank",
    "score": 0.66,
    "bbox": {
      "min_lon": 4.3480438257437175,
      "min_lat": 51.88997437648539,
      "max_lon": 4.348141264774938,
      "max_lat": 51.890121524642815
    },
    "center": {
      "lon": 4.348092545185005,
      "lat": 51.890047950602174
    }
  },
  {
    "file": "SN6_Train_AOI_11_Rotterdam_PS-RGB_20190804111224_20190804111453_tile_8681.tif",
    "label": "vehicle",
    "score": 0.61,
    "bbox": {
      "min_lon": 4.353252886217651,
      "min_lat": 51.88804559894302,
      "max_lon": 4.353470531453671,
      "max_lat": 51.88819020890287
    },
    "center": {
      "lon": 4.3533617086679985,
      "lat": 51.88811790395721
    }
  },
  {
    "file": "SN6_Train_AOI_11_Rotterdam_PS-RGB_20190804111224_20190804111453_tile_8681.tif",
    "label": "vehicle",
    "score": 0.58,
    "bbox": {
      "min_lon": 4.353177743743213,
      "min_lat": 51.88826072801943,
      "max_lon": 4.3534071921992545,
      "max_lat": 51.8884112203122
    },
    "center": {
      "lon": 4.353292467787255,
      "lat": 51.888335974202846
    }
  },
  {
    "file": "SN6_Train_AOI_11_Rotterdam_PS-RGB_20190804111224_20190804111453_tile_8681.tif",
    "label": "vehicle",
    "score": 0.57,
    "bbox": {
      "min_lon": 4.3518107235657775,
      "min_lat": 51.88900130419812,
      "max_lon": 4.352067889339561,
      "max_lat": 51.88907122083765
    },
    "center": {
      "lon": 4.3519393063572975,
      "lat": 51.889036262524435
    }
  },
  {
    "file": "SN6_Train_AOI_11_Rotterdam_PS-RGB_20190804111224_20190804111453_tile_8681.tif",
    "label": "vehicle",
    "score": 0.46,
    "bbox": {
      "min_lon": 4.352301715186156,
      "min_lat": 51.888803248656174,
      "max_lon": 4.352569525757973,
      "max_lat": 51.888925423447176
    },
    "center": {
      "lon": 4.352435620297383,
      "lat": 51.888864336074704
    }
  },
  {
    "file": "SN6_Train_AOI_11_Rotterdam_PS-RGB_20190804111224_20190804111453_tile_8681.tif",
    "label": "vehicle",
    "score": 0.43,
    "bbox": {
      "min_lon": 4.352436578257318,
      "min_lat": 51.88882680349126,
      "max_lon": 4.3526821420829345,
      "max_lat": 51.88894275049713
    },
    "center": {
      "lon": 4.352559360018114,
      "lat": 51.88888477701507
    }
  },
  {
    "file": "SN6_Train_AOI_11_Rotterdam_PS-RGB_20190804111224_20190804111453_tile_8681.tif",
    "label": "vehicle",
    "score": 0.43,
    "bbox": {
      "min_lon": 4.353226431348017,
      "min_lat": 51.88818884039059,
      "max_lon": 4.353432283470585,
      "max_lat": 51.88832295839794
    },
    "center": {
      "lon": 4.353329357262192,
      "lat": 51.88825589942365
    }
  },
  {
    "file": "SN6_Train_AOI_11_Rotterdam_PS-RGB_20190804111224_20190804111453_tile_8683.tif",
    "label": "storagetank",
    "score": 0.98,
    "bbox": {
      "min_lon": 4.360069733239569,
      "min_lat": 51.889725991927136,
      "max_lon": 4.3606283543961455,
      "max_lat": 51.89007565780612
    },
    "center": {
      "lon": 4.360349042776716,
      "lat": 51.88990082506517
    }
  },
  {
    "file": "SN6_Train_AOI_11_Rotterdam_PS-RGB_20190804111224_20190804111453_tile_8683.tif",
    "label": "storagetank",
    "score": 0.97,
    "bbox": {
      "min_lon": 4.360302382446085,
      "min_lat": 51.89015188545431,
      "max_lon": 4.360763926042015,
      "max_lat": 51.890427856585774
    },
    "center": {
      "lon": 4.36053315356482,
      "lat": 51.89028987114292
    }
  },
  {
    "file": "SN6_Train_AOI_11_Rotterdam_PS-RGB_20190804111224_20190804111453_tile_8683.tif",
    "label": "storagetank",
    "score": 0.97,
    "bbox": {
      "min_lon": 4.357115554634782,
      "min_lat": 51.890404493482265,
      "max_lon": 4.357601201658815,
      "max_lat": 51.89067439638775
    },
    "center": {
      "lon": 4.357358377447355,
      "lat": 51.890539445051274
    }
  },
  {
    "file": "SN6_Train_AOI_11_Rotterdam_PS-RGB_20190804111224_20190804111453_tile_8683.tif",
    "label": "storagetank",
    "score": 0.96,
    "bbox": {
      "min_lon": 4.3576481014373565,
      "min_lat": 51.89047638305093,
      "max_lon": 4.358124835017931,
      "max_lat": 51.890728085438795
    },
    "center": {
      "lon": 4.3578864675871865,
      "lat": 51.890602234345145
    }
  },
  {
    "file": "SN6_Train_AOI_11_Rotterdam_PS-RGB_20190804111224_20190804111453_tile_8683.tif",
    "label": "storagetank",
    "score": 0.96,
    "bbox": {
      "min_lon": 4.359876469619018,
      "min_lat": 51.890401761160604,
      "max_lon": 4.360328134647343,
      "max_lat": 51.89068075677714
    },
    "center": {
      "lon": 4.360102301461397,
      "lat": 51.89054125909504
    }
  },
  {
    "file": "SN6_Train_AOI_11_Rotterdam_PS-RGB_20190804111224_20190804111453_tile_8683.tif",
    "label": "storagetank",
    "score": 0.95,
    "bbox": {
      "min_lon": 4.359103825241195,
      "min_lat": 51.89010891990108,
      "max_lon": 4.35929230113886,
      "max_lat": 51.890222460045656
    },
    "center": {
      "lon": 4.359198063075916,
      "lat": 51.8901656899942
    }
  },
  {
    "file": "SN6_Train_AOI_11_Rotterdam_PS-RGB_20190804111224_20190804111453_tile_8683.tif",
    "label": "storagetank",
    "score": 0.93,
    "bbox": {
      "min_lon": 4.3591340737106385,
      "min_lat": 51.889980842741956,
      "max_lon": 4.359328828083727,
      "max_lat": 51.89009667165597
    },
    "center": {
      "lon": 4.3592314507768775,
      "lat": 51.890038757220594
    }
  },
  {
    "file": "SN6_Train_AOI_11_Rotterdam_PS-RGB_20190804111224_20190804111453_tile_8683.tif",
    "label": "storagetank",
    "score": 0.92,
    "bbox": {
      "min_lon": 4.359228080993326,
      "min_lat": 51.88972824117536,
      "max_lon": 4.359391684799034,
      "max_lat": 51.889828467422404
    },
    "center": {
      "lon": 4.3593098828087555,
      "lat": 51.88977835431513
    }
  },
  {
    "file": "SN6_Train_AOI_11_Rotterdam_PS-RGB_20190804111224_20190804111453_tile_8683.tif",
    "label": "storagetank",
    "score": 0.92,
    "bbox": {
      "min_lon": 4.358205311334068,
      "min_lat": 51.89053159068151,
      "max_lon": 4.358649711388017,
      "max_lat": 51.89080098848951
    },
    "center": {
      "lon": 4.3584275107226516,
      "lat": 51.890666289702864
    }
  },
  {
    "file": "SN6_Train_AOI_11_Rotterdam_PS-RGB_20190804111224_20190804111453_tile_8683.tif",
    "label": "storagetank",
    "score": 0.92,
    "bbox": {
      "min_lon": 4.359378982248608,
      "min_lat": 51.88987892762688,
      "max_lon": 4.359589173669599,
      "max_lat": 51.88999986234773
    },
    "center": {
      "lon": 4.359484077823505,
      "lat": 51.88993939501077
    }
  },
  {
    "file": "SN6_Train_AOI_11_Rotterdam_PS-RGB_20190804111224_20190804111453_tile_8683.tif",
    "label": "storagetank",
    "score": 0.92,
    "bbox": {
      "min_lon": 4.359428964919095,
      "min_lat": 51.88975325864182,
      "max_lon": 4.359585358271724,
      "max_lat": 51.889848231555575
    },
    "center": {
      "lon": 4.359507161516214,
      "lat": 51.88980074511327
    }
  },
  {
    "file": "SN6_Train_AOI_11_Rotterdam_PS-RGB_20190804111224_20190804111453_tile_8683.tif",
    "label": "storagetank",
    "score": 0.91,
    "bbox": {
      "min_lon": 4.359342521577801,
      "min_lat": 51.89000315582802,
      "max_lon": 4.3595376834507125,
      "max_lat": 51.890118554049
    },
    "center": {
      "lon": 4.359440102394146,
      "lat": 51.89006085495997
    }
  },
  {
    "file": "SN6_Train_AOI_11_Rotterdam_PS-RGB_20190804111224_20190804111453_tile_8683.tif",
    "label": "storagetank",
    "score": 0.89,
    "bbox": {
      "min_lon": 4.3592610870131345,
      "min_lat": 51.8896201815557,
      "max_lon": 4.359430629783619,
      "max_lat": 51.88972281303085
    },
    "center": {
      "lon": 4.359345858305598,
      "lat": 51.88967149731031
    }
  },
  {
    "file": "SN6_Train_AOI_11_Rotterdam_PS-RGB_20190804111224_20190804111453_tile_8683.tif",
    "label": "storagetank",
    "score": 0.85,
    "bbox": {
      "min_lon": 4.359458927176081,
      "min_lat": 51.88964981448497,
      "max_lon": 4.359621585950183,
      "max_lat": 51.889747806662314
    },
    "center": {
      "lon": 4.359540256478138,
      "lat": 51.88969881058915
    }
  },
  {
    "file": "SN6_Train_AOI_11_Rotterdam_PS-RGB_20190804111224_20190804111453_tile_8683.tif",
    "label": "storagetank",
    "score": 0.83,
    "bbox": {
      "min_lon": 4.359299028958781,
      "min_lat": 51.890130146015245,
      "max_lon": 4.359503111952949,
      "max_lat": 51.89024963072459
    },
    "center": {
      "lon": 4.359401070325803,
      "lat": 51.89018988839288
    }
  },
  {
    "file": "SN6_Train_AOI_11_Rotterdam_PS-RGB_20190804111224_20190804111453_tile_8683.tif",
    "label": "storagetank",
    "score": 0.82,
    "bbox": {
      "min_lon": 4.359210232220235,
      "min_lat": 51.889879025794684,
      "max_lon": 4.359335415650118,
      "max_lat": 51.8899551131623
    },
    "center": {
      "lon": 4.359272823884392,
      "lat": 51.88991706948786
    }
  },
  {
    "file": "SN6_Train_AOI_11_Rotterdam_PS-RGB_20190804111224_20190804111453_tile_8683.tif",
    "label": "storagetank",
    "score": 0.81,
    "bbox": {
      "min_lon": 4.358720824295676,
      "min_lat": 51.89059192965524,
      "max_lon": 4.359203939522541,
      "max_lat": 51.890816915919395
    },
    "center": {
      "lon": 4.3589623813288725,
      "lat": 51.89070442286564
    }
  },
  {
    "file": "SN6_Train_AOI_11_Rotterdam_PS-RGB_20190804111224_20190804111453_tile_8683.tif",
    "label": "storagetank",
    "score": 0.81,
    "bbox": {
      "min_lon": 4.359324812607365,
      "min_lat": 51.88944251770805,
      "max_lon": 4.3595199520981005,
      "max_lat": 51.889553762030246
    },
    "center": {
      "lon": 4.359422382236929,
      "lat": 51.88949813988897
    }
  },
  {
    "file": "SN6_Train_AOI_11_Rotterdam_PS-RGB_20190804111224_20190804111453_tile_8683.tif",
    "label": "storagetank",
    "score": 0.79,
    "bbox": {
      "min_lon": 4.356369072220981,
      "min_lat": 51.890214502320724,
      "max_lon": 4.356631923291405,
      "max_lat": 51.890369814515346
    },
    "center": {
      "lon": 4.356500497538444,
      "lat": 51.890292158456894
    }
  },
  {
    "file": "SN6_Train_AOI_11_Rotterdam_PS-RGB_20190804111224_20190804111453_tile_8683.tif",
    "label": "ship",
    "score": 0.77,
    "bbox": {
      "min_lon": 4.357307323343987,
      "min_lat": 51.88779970881422,
      "max_lon": 4.3580108300294,
      "max_lat": 51.888011407952
    },
    "center": {
      "lon": 4.357659075895174,
      "lat": 51.887905558445226
    }
  },
  {
    "file": "SN6_Train_AOI_11_Rotterdam_PS-RGB_20190804111224_20190804111453_tile_8683.tif",
    "label": "storagetank",
    "score": 0.76,
    "bbox": {
      "min_lon": 4.359212819816386,
      "min_lat": 51.88944461484102,
      "max_lon": 4.359332766038915,
      "max_lat": 51.889512755500306
    },
    "center": {
      "lon": 4.359272792884046,
      "lat": 51.889478685178084
    }
  },
  {
    "file": "SN6_Train_AOI_11_Rotterdam_PS-RGB_20190804111224_20190804111453_tile_8683.tif",
    "label": "storagetank",
    "score": 0.75,
    "bbox": {
      "min_lon": 4.358730560703184,
      "min_lat": 51.88998150323617,
      "max_lon": 4.358834051863147,
      "max_lat": 51.890041382074436
    },
    "center": {
      "lon": 4.358782306250109,
      "lat": 51.89001144266106
    }
  },
  {
    "file": "SN6_Train_AOI_11_Rotterdam_PS-RGB_20190804111224_20190804111453_tile_8683.tif",
    "label": "storagetank",
    "score": 0.72,
    "bbox": {
      "min_lon": 4.358829403508353,
      "min_lat": 51.889827153703855,
      "max_lon": 4.358945731363752,
      "max_lat": 51.8898980352841
    },
    "center": {
      "lon": 4.358887567392088,
      "lat": 51.8898625945021
    }
  },
  {
    "file": "SN6_Train_AOI_11_Rotterdam_PS-RGB_20190804111224_20190804111453_tile_8683.tif",
    "label": "storagetank",
    "score": 0.68,
    "bbox": {
      "min_lon": 4.357445335664165,
      "min_lat": 51.889946671621566,
      "max_lon": 4.357641829300765,
      "max_lat": 51.89005686234289
    },
    "center": {
      "lon": 4.357543582366938,
      "lat": 51.890001767001635
    }
  },
  {
    "file": "SN6_Train_AOI_11_Rotterdam_PS-RGB_20190804111224_20190804111453_tile_8683.tif",
    "label": "storagetank",
    "score": 0.67,
    "bbox": {
      "min_lon": 4.358767816548873,
      "min_lat": 51.889893592015454,
      "max_lon": 4.35885090398222,
      "max_lat": 51.889943466472964
    },
    "center": {
      "lon": 4.358809360243447,
      "lat": 51.88991852924822
    }
  },
  {
    "file": "SN6_Train_AOI_11_Rotterdam_PS-RGB_20190804111224_20190804111453_tile_8683.tif",
    "label": "ship",
    "score": 0.65,
    "bbox": {
      "min_lon": 4.360558547081313,
      "min_lat": 51.88909089006315,
      "max_lon": 4.361103277227511,
      "max_lat": 51.88934595866714
    },
    "center": {
      "lon": 4.3608309114127755,
      "lat": 51.889218424465874
    }
  },
  {
    "file": "SN6_Train_AOI_11_Rotterdam_PS-RGB_20190804111224_20190804111453_tile_8683.tif",
    "label": "vehicle",
    "score": 0.49,
    "bbox": {
      "min_lon": 4.358174264651093,
      "min_lat": 51.888987137058194,
      "max_lon": 4.35825454765372,
      "max_lat": 51.88904495460804
    },
    "center": {
      "lon": 4.358214406127713,
      "lat": 51.88901604583864
    }
  },
  {
    "file": "SN6_Train_AOI_11_Rotterdam_PS-RGB_20190804111224_20190804111453_tile_8685.tif",
    "label": "storagetank",
    "score": 0.96,
    "bbox": {
      "min_lon": 4.362540990373187,
      "min_lat": 51.89047086309568,
      "max_lon": 4.36301713860525,
      "max_lat": 51.89076784832275
    },
    "center": {
      "lon": 4.362779063735493,
      "lat": 51.89061935585235
    }
  },
  {
    "file": "SN6_Train_AOI_11_Rotterdam_PS-RGB_20190804111224_20190804111453_tile_8685.tif",
    "label": "storagetank",
    "score": 0.94,
    "bbox": {
      "min_lon": 4.361128702584419,
      "min_lat": 51.89017352530748,
      "max_lon": 4.3616747708579195,
      "max_lat": 51.89051377615814
    },
    "center": {
      "lon": 4.361401735730792,
      "lat": 51.89034365092066
    }
  },
  {
    "file": "SN6_Train_AOI_11_Rotterdam_PS-RGB_20190804111224_20190804111453_tile_8685.tif",
    "label": "ship",
    "score": 0.92,
    "bbox": {
      "min_lon": 4.361100096135079,
      "min_lat": 51.88922566646741,
      "max_lon": 4.361736920718911,
      "max_lat": 51.889526425378335
    },
    "center": {
      "lon": 4.361418507404669,
      "lat": 51.88937604606315
    }
  },
  {
    "file": "SN6_Train_AOI_11_Rotterdam_PS-RGB_20190804111224_20190804111453_tile_8685.tif",
    "label": "ship",
    "score": 0.67,
    "bbox": {
      "min_lon": 4.3623426059877195,
      "min_lat": 51.88938745626922,
      "max_lon": 4.363677534942603,
      "max_lat": 51.889916012250275
    },
    "center": {
      "lon": 4.363010066701826,
      "lat": 51.88965173467703
    }
  },
  {
    "file": "SN6_Train_AOI_11_Rotterdam_PS-RGB_20190804111224_20190804111453_tile_8685.tif",
    "label": "ship",
    "score": 0.62,
    "bbox": {
      "min_lon": 4.366924458347641,
      "min_lat": 51.88813830054654,
      "max_lon": 4.367616971829731,
      "max_lat": 51.88850532547837
    },
    "center": {
      "lon": 4.367270713732575,
      "lat": 51.888321813225524
    }
  },
  {
    "file": "SN6_Train_AOI_11_Rotterdam_PS-RGB_20190804111224_20190804111453_tile_8685.tif",
    "label": "ship",
    "score": 0.54,
    "bbox": {
      "min_lon": 4.367362321858661,
      "min_lat": 51.890130067113745,
      "max_lon": 4.367637380412371,
      "max_lat": 51.89033646400356
    },
    "center": {
      "lon": 4.36749985083379,
      "lat": 51.890233265629384
    }
  },
  {
    "file": "SN6_Train_AOI_11_Rotterdam_PS-RGB_20190804111224_20190804111453_tile_8685.tif",
    "label": "ship",
    "score": 0.43,
    "bbox": {
      "min_lon": 4.367416042077602,
      "min_lat": 51.889624741988314,
      "max_lon": 4.367662209818302,
      "max_lat": 51.88999026895112
    },
    "center": {
      "lon": 4.367539125481531,
      "lat": 51.889807505704226
    }
  },
  {
    "file": "SN6_Train_AOI_11_Rotterdam_PS-RGB_20190804111224_20190804111453_tile_8687.tif",
    "label": "storagetank",
    "score": 0.96,
    "bbox": {
      "min_lon": 4.372032093611951,
      "min_lat": 51.88929154802791,
      "max_lon": 4.372363663868767,
      "max_lat": 51.88947499742659
    },
    "center": {
      "lon": 4.372197878415928,
      "lat": 51.88938327278084
    }
  },
  {
    "file": "SN6_Train_AOI_11_Rotterdam_PS-RGB_20190804111224_20190804111453_tile_8687.tif",
    "label": "storagetank",
    "score": 0.95,
    "bbox": {
      "min_lon": 4.373833664383695,
      "min_lat": 51.8893750383883,
      "max_lon": 4.374152698539083,
      "max_lat": 51.88956074753493
    },
    "center": {
      "lon": 4.373993181145505,
      "lat": 51.88946789301694
    }
  },
  {
    "file": "SN6_Train_AOI_11_Rotterdam_PS-RGB_20190804111224_20190804111453_tile_8687.tif",
    "label": "storagetank",
    "score": 0.93,
    "bbox": {
      "min_lon": 4.373616300022484,
      "min_lat": 51.88892787611547,
      "max_lon": 4.37378494967514,
      "max_lat": 51.88903445691466
    },
    "center": {
      "lon": 4.373700624753052,
      "lat": 51.8889811665335
    }
  },
  {
    "file": "SN6_Train_AOI_11_Rotterdam_PS-RGB_20190804111224_20190804111453_tile_8687.tif",
    "label": "storagetank",
    "score": 0.93,
    "bbox": {
      "min_lon": 4.371448043300467,
      "min_lat": 51.889102146118205,
      "max_lon": 4.37181622786579,
      "max_lat": 51.889288035748
    },
    "center": {
      "lon": 4.371632135217943,
      "lat": 51.889195090987286
    }
  },
  {
    "file": "SN6_Train_AOI_11_Rotterdam_PS-RGB_20190804111224_20190804111453_tile_8687.tif",
    "label": "storagetank",
    "score": 0.91,
    "bbox": {
      "min_lon": 4.372470842487427,
      "min_lat": 51.8889950221252,
      "max_lon": 4.372771712902283,
      "max_lat": 51.889181245859604
    },
    "center": {
      "lon": 4.372621277396291,
      "lat": 51.88908813404855
    }
  },
  {
    "file": "SN6_Train_AOI_11_Rotterdam_PS-RGB_20190804111224_20190804111453_tile_8687.tif",
    "label": "storagetank",
    "score": 0.89,
    "bbox": {
      "min_lon": 4.373558095347621,
      "min_lat": 51.88881371849669,
      "max_lon": 4.3737368422306915,
      "max_lat": 51.88892178746901
    },
    "center": {
      "lon": 4.373647468686202,
      "lat": 51.88886775300169
    }
  },
  {
    "file": "SN6_Train_AOI_11_Rotterdam_PS-RGB_20190804111224_20190804111453_tile_8687.tif",
    "label": "storagetank",
    "score": 0.89,
    "bbox": {
      "min_lon": 4.373667468306184,
      "min_lat": 51.889038096613156,
      "max_lon": 4.373846360018824,
      "max_lat": 51.889146692122324
    },
    "center": {
      "lon": 4.3737569140589665,
      "lat": 51.88909239438677
    }
  },
  {
    "file": "SN6_Train_AOI_11_Rotterdam_PS-RGB_20190804111224_20190804111453_tile_8687.tif",
    "label": "storagetank",
    "score": 0.89,
    "bbox": {
      "min_lon": 4.373719003602185,
      "min_lat": 51.88915091378648,
      "max_lon": 4.373905593620575,
      "max_lat": 51.88926106956317
    },
    "center": {
      "lon": 4.3738122985018055,
      "lat": 51.88920599169434
    }
  },
  {
    "file": "SN6_Train_AOI_11_Rotterdam_PS-RGB_20190804111224_20190804111453_tile_8687.tif",
    "label": "storagetank",
    "score": 0.88,
    "bbox": {
      "min_lon": 4.371052693878922,
      "min_lat": 51.88917140829977,
      "max_lon": 4.37137648722875,
      "max_lat": 51.88935748380537
    },
    "center": {
      "lon": 4.371214590232549,
      "lat": 51.88926444610803
    }
  },
  {
    "file": "SN6_Train_AOI_11_Rotterdam_PS-RGB_20190804111224_20190804111453_tile_8687.tif",
    "label": "storagetank",
    "score": 0.88,
    "bbox": {
      "min_lon": 4.372554749360478,
      "min_lat": 51.88919324961044,
      "max_lon": 4.372824453188757,
      "max_lat": 51.88935414588911
    },
    "center": {
      "lon": 4.372689601043297,
      "lat": 51.88927369779147
    }
  },
  {
    "file": "SN6_Train_AOI_11_Rotterdam_PS-RGB_20190804111224_20190804111453_tile_8687.tif",
    "label": "storagetank",
    "score": 0.87,
    "bbox": {
      "min_lon": 4.371606083544677,
      "min_lat": 51.88936660267486,
      "max_lon": 4.371928163727147,
      "max_lat": 51.88954696936459
    },
    "center": {
      "lon": 4.37176712332608,
      "lat": 51.88945678607163
    }
  },
  {
    "file": "SN6_Train_AOI_11_Rotterdam_PS-RGB_20190804111224_20190804111453_tile_8687.tif",
    "label": "storagetank",
    "score": 0.86,
    "bbox": {
      "min_lon": 4.371956776464933,
      "min_lat": 51.88906095081132,
      "max_lon": 4.37219752153955,
      "max_lat": 51.88919247699666
    },
    "center": {
      "lon": 4.372077148833342,
      "lat": 51.88912671393148
    }
  },
  {
    "file": "SN6_Train_AOI_11_Rotterdam_PS-RGB_20190804111224_20190804111453_tile_8687.tif",
    "label": "storagetank",
    "score": 0.84,
    "bbox": {
      "min_lon": 4.373958002105195,
      "min_lat": 51.889239431706464,
      "max_lon": 4.374132755819893,
      "max_lat": 51.889340851578616
    },
    "center": {
      "lon": 4.374045378868047,
      "lat": 51.88929014165904
    }
  },
  {
    "file": "SN6_Train_AOI_11_Rotterdam_PS-RGB_20190804111224_20190804111453_tile_8687.tif",
    "label": "storagetank",
    "score": 0.84,
    "bbox": {
      "min_lon": 4.373774755950311,
      "min_lat": 51.88926444855309,
      "max_lon": 4.373956843033441,
      "max_lat": 51.88937212751183
    },
    "center": {
      "lon": 4.373865799387355,
      "lat": 51.88931828805111
    }
  },
  {
    "file": "SN6_Train_AOI_11_Rotterdam_PS-RGB_20190804111224_20190804111453_tile_8687.tif",
    "label": "storagetank",
    "score": 0.82,
    "bbox": {
      "min_lon": 4.372812093551147,
      "min_lat": 51.889140129798434,
      "max_lon": 4.373159267831511,
      "max_lat": 51.88931905314986
    },
    "center": {
      "lon": 4.372985680359914,
      "lat": 51.889229591524504
    }
  },
  {
    "file": "SN6_Train_AOI_11_Rotterdam_PS-RGB_20190804111224_20190804111453_tile_8687.tif",
    "label": "storagetank",
    "score": 0.79,
    "bbox": {
      "min_lon": 4.373916351906497,
      "min_lat": 51.8891298112073,
      "max_lon": 4.374071609660649,
      "max_lat": 51.88922179301508
    },
    "center": {
      "lon": 4.3739939807074455,
      "lat": 51.88917580212481
    }
  },
  {
    "file": "SN6_Train_AOI_11_Rotterdam_PS-RGB_20190804111224_20190804111453_tile_8687.tif",
    "label": "storagetank",
    "score": 0.78,
    "bbox": {
      "min_lon": 4.373871370033327,
      "min_lat": 51.88901135029256,
      "max_lon": 4.374056501738415,
      "max_lat": 51.88911380209892
    },
    "center": {
      "lon": 4.373963935784712,
      "lat": 51.88906257621245
    }
  },
  {
    "file": "SN6_Train_AOI_11_Rotterdam_PS-RGB_20190804111224_20190804111453_tile_8687.tif",
    "label": "ship",
    "score": 0.76,
    "bbox": {
      "min_lon": 4.367597272690668,
      "min_lat": 51.88782381796533,
      "max_lon": 4.369605191705174,
      "max_lat": 51.88844991109749
    },
    "center": {
      "lon": 4.368601225514503,
      "lat": 51.88813686507954
    }
  },
  {
    "file": "SN6_Train_AOI_11_Rotterdam_PS-RGB_20190804111224_20190804111453_tile_8687.tif",
    "label": "ship",
    "score": 0.69,
    "bbox": {
      "min_lon": 4.367639785788901,
      "min_lat": 51.88924485201996,
      "max_lon": 4.367868416102486,
      "max_lat": 51.88958493329475
    },
    "center": {
      "lon": 4.367754100542705,
      "lat": 51.88941489286035
    }
  },
  {
    "file": "SN6_Train_AOI_11_Rotterdam_PS-RGB_20190804111224_20190804111453_tile_8687.tif",
    "label": "storagetank",
    "score": 0.67,
    "bbox": {
      "min_lon": 4.373521938593998,
      "min_lat": 51.88870902034868,
      "max_lon": 4.373654622332696,
      "max_lat": 51.88879248485872
    },
    "center": {
      "lon": 4.373588280404347,
      "lat": 51.888750752615
    }
  },
  {
    "file": "SN6_Train_AOI_11_Rotterdam_PS-RGB_20190804111224_20190804111453_tile_8687.tif",
    "label": "storagetank",
    "score": 0.54,
    "bbox": {
      "min_lon": 4.373832840601049,
      "min_lat": 51.88891364710151,
      "max_lon": 4.373957172444927,
      "max_lat": 51.88898962529863
    },
    "center": {
      "lon": 4.373895006472643,
      "lat": 51.8889516362094
    }
  },
  {
    "file": "SN6_Train_AOI_11_Rotterdam_PS-RGB_20190804111224_20190804111453_tile_8687.tif",
    "label": "vehicle",
    "score": 0.53,
    "bbox": {
      "min_lon": 4.371955644589693,
      "min_lat": 51.890064698307725,
      "max_lon": 4.372071856014291,
      "max_lat": 51.89015687975461
    },
    "center": {
      "lon": 4.372013750245129,
      "lat": 51.89011078904536
    }
  },
  {
    "file": "SN6_Train_AOI_11_Rotterdam_PS-RGB_20190804111224_20190804111453_tile_8687.tif",
    "label": "vehicle",
    "score": 0.48,
    "bbox": {
      "min_lon": 4.37229582538311,
      "min_lat": 51.890063877755395,
      "max_lon": 4.372479825463468,
      "max_lat": 51.89021837563098
    },
    "center": {
      "lon": 4.3723878252725905,
      "lat": 51.89014112673329
    }
  },
  {
    "file": "SN6_Train_AOI_11_Rotterdam_PS-RGB_20190804111224_20190804111453_tile_8689.tif",
    "label": "storagetank",
    "score": 0.93,
    "bbox": {
      "min_lon": 4.37614152229449,
      "min_lat": 51.88840552200363,
      "max_lon": 4.376503106249241,
      "max_lat": 51.88862124432719
    },
    "center": {
      "lon": 4.376322313856121,
      "lat": 51.88851338324033
    }
  },
  {
    "file": "SN6_Train_AOI_11_Rotterdam_PS-RGB_20190804111224_20190804111453_tile_8689.tif",
    "label": "storagetank",
    "score": 0.92,
    "bbox": {
      "min_lon": 4.377283035332635,
      "min_lat": 51.88831721838566,
      "max_lon": 4.3775204224512825,
      "max_lat": 51.88845645534792
    },
    "center": {
      "lon": 4.3774017287157685,
      "lat": 51.888386836897915
    }
  },
  {
    "file": "SN6_Train_AOI_11_Rotterdam_PS-RGB_20190804111224_20190804111453_tile_8689.tif",
    "label": "storagetank",
    "score": 0.91,
    "bbox": {
      "min_lon": 4.375570397694237,
      "min_lat": 51.88851122006455,
      "max_lon": 4.375697029817741,
      "max_lat": 51.888587636001276
    },
    "center": {
      "lon": 4.375633713704416,
      "lat": 51.88854942804233
    }
  },
  {
    "file": "SN6_Train_AOI_11_Rotterdam_PS-RGB_20190804111224_20190804111453_tile_8689.tif",
    "label": "storagetank",
    "score": 0.88,
    "bbox": {
      "min_lon": 4.375681536531026,
      "min_lat": 51.88835865143099,
      "max_lon": 4.3758427002370945,
      "max_lat": 51.88845798816575
    },
    "center": {
      "lon": 4.375762118298757,
      "lat": 51.88840831981434
    }
  },
  {
    "file": "SN6_Train_AOI_11_Rotterdam_PS-RGB_20190804111224_20190804111453_tile_8689.tif",
    "label": "storagetank",
    "score": 0.87,
    "bbox": {
      "min_lon": 4.377196461159177,
      "min_lat": 51.888138321700396,
      "max_lon": 4.3774292149366625,
      "max_lat": 51.88827970451197
    },
    "center": {
      "lon": 4.377312837872562,
      "lat": 51.88820901313845
    }
  },
  {
    "file": "SN6_Train_AOI_11_Rotterdam_PS-RGB_20190804111224_20190804111453_tile_8689.tif",
    "label": "storagetank",
    "score": 0.87,
    "bbox": {
      "min_lon": 4.376611880858417,
      "min_lat": 51.88844122917984,
      "max_lon": 4.376802508118334,
      "max_lat": 51.888554086194986
    },
    "center": {
      "lon": 4.376707194373703,
      "lat": 51.888497657707894
    }
  },
  {
    "file": "SN6_Train_AOI_11_Rotterdam_PS-RGB_20190804111224_20190804111453_tile_8689.tif",
    "label": "storagetank",
    "score": 0.87,
    "bbox": {
      "min_lon": 4.375714611619239,
      "min_lat": 51.888472129957435,
      "max_lon": 4.375855609970992,
      "max_lat": 51.88855244929589
    },
    "center": {
      "lon": 4.375785110734732,
      "lat": 51.88851228963697
    }
  },
  {
    "file": "SN6_Train_AOI_11_Rotterdam_PS-RGB_20190804111224_20190804111453_tile_8689.tif",
    "label": "storagetank",
    "score": 0.85,
    "bbox": {
      "min_lon": 4.37553002671731,
      "min_lat": 51.88841643941894,
      "max_lon": 4.3756636382417495,
      "max_lat": 51.88849847099426
    },
    "center": {
      "lon": 4.375596832421126,
      "lat": 51.88845745521748
    }
  },
  {
    "file": "SN6_Train_AOI_11_Rotterdam_PS-RGB_20190804111224_20190804111453_tile_8689.tif",
    "label": "storagetank",
    "score": 0.84,
    "bbox": {
      "min_lon": 4.376935246293892,
      "min_lat": 51.88827354221235,
      "max_lon": 4.37707592017298,
      "max_lat": 51.88835542952203
    },
    "center": {
      "lon": 4.377005583172026,
      "lat": 51.88831448587794
    }
  },
  {
    "file": "SN6_Train_AOI_11_Rotterdam_PS-RGB_20190804111224_20190804111453_tile_8689.tif",
    "label": "storagetank",
    "score": 0.82,
    "bbox": {
      "min_lon": 4.375754978371943,
      "min_lat": 51.888564252136156,
      "max_lon": 4.375888530696622,
      "max_lat": 51.888642018489904
    },
    "center": {
      "lon": 4.375821754478914,
      "lat": 51.88860313532274
    }
  },
  {
    "file": "SN6_Train_AOI_11_Rotterdam_PS-RGB_20190804111224_20190804111453_tile_8689.tif",
    "label": "storagetank",
    "score": 0.81,
    "bbox": {
      "min_lon": 4.376892552513883,
      "min_lat": 51.888374095607446,
      "max_lon": 4.3770351944803,
      "max_lat": 51.88845745646072
    },
    "center": {
      "lon": 4.376963873433708,
      "lat": 51.88841577604524
    }
  },
  {
    "file": "SN6_Train_AOI_11_Rotterdam_PS-RGB_20190804111224_20190804111453_tile_8689.tif",
    "label": "storagetank",
    "score": 0.81,
    "bbox": {
      "min_lon": 4.375608474166054,
      "min_lat": 51.8886042319762,
      "max_lon": 4.375730789162258,
      "max_lat": 51.88867774248175
    },
    "center": {
      "lon": 4.375669631616236,
      "lat": 51.88864098723769
    }
  },
  {
    "file": "SN6_Train_AOI_11_Rotterdam_PS-RGB_20190804111224_20190804111453_tile_8689.tif",
    "label": "storagetank",
    "score": 0.81,
    "bbox": {
      "min_lon": 4.375715064350906,
      "min_lat": 51.89054351560713,
      "max_lon": 4.37582944814725,
      "max_lat": 51.89061166362347
    },
    "center": {
      "lon": 4.375772256207528,
      "lat": 51.89057758962277
    }
  },
  {
    "file": "SN6_Train_AOI_11_Rotterdam_PS-RGB_20190804111224_20190804111453_tile_8689.tif",
    "label": "storagetank",
    "score": 0.8,
    "bbox": {
      "min_lon": 4.375492025306557,
      "min_lat": 51.88861197414446,
      "max_lon": 4.375602813625565,
      "max_lat": 51.888678988412735
    },
    "center": {
      "lon": 4.3755474194264945,
      "lat": 51.88864548128584
    }
  },
  {
    "file": "SN6_Train_AOI_11_Rotterdam_PS-RGB_20190804111224_20190804111453_tile_8689.tif",
    "label": "Expressway-toll-station",
    "score": 0.75,
    "bbox": {
      "min_lon": 4.377025519324608,
      "min_lat": 51.88909890473242,
      "max_lon": 4.377607143203529,
      "max_lat": 51.88938060686437
    },
    "center": {
      "lon": 4.377316330389925,
      "lat": 51.88923975592178
    }
  },
  {
    "file": "SN6_Train_AOI_11_Rotterdam_PS-RGB_20190804111224_20190804111453_tile_8689.tif",
    "label": "storagetank",
    "score": 0.75,
    "bbox": {
      "min_lon": 4.37580601886126,
      "min_lat": 51.89044212762811,
      "max_lon": 4.375925405959835,
      "max_lat": 51.89051310840239
    },
    "center": {
      "lon": 4.375865712365377,
      "lat": 51.89047761802336
    }
  },
  {
    "file": "SN6_Train_AOI_11_Rotterdam_PS-RGB_20190804111224_20190804111453_tile_8689.tif",
    "label": "storagetank",
    "score": 0.74,
    "bbox": {
      "min_lon": 4.37668808339352,
      "min_lat": 51.88832555399306,
      "max_lon": 4.376853300940675,
      "max_lat": 51.88841848925386
    },
    "center": {
      "lon": 4.3767706920852225,
      "lat": 51.888372021637245
    }
  },
  {
    "file": "SN6_Train_AOI_11_Rotterdam_PS-RGB_20190804111224_20190804111453_tile_8689.tif",
    "label": "storagetank",
    "score": 0.72,
    "bbox": {
      "min_lon": 4.374196151933688,
      "min_lat": 51.88935326701182,
      "max_lon": 4.374312761939,
      "max_lat": 51.88941957046401
    },
    "center": {
      "lon": 4.374254456895116,
      "lat": 51.88938641874494
    }
  },
  {
    "file": "SN6_Train_AOI_11_Rotterdam_PS-RGB_20190804111224_20190804111453_tile_8689.tif",
    "label": "storagetank",
    "score": 0.72,
    "bbox": {
      "min_lon": 4.3758323882467645,
      "min_lat": 51.888655387264315,
      "max_lon": 4.375942457708766,
      "max_lat": 51.88872094375354
    },
    "center": {
      "lon": 4.3758874229393045,
      "lat": 51.88868816551584
    }
  },
  {
    "file": "SN6_Train_AOI_11_Rotterdam_PS-RGB_20190804111224_20190804111453_tile_8689.tif",
    "label": "storagetank",
    "score": 0.72,
    "bbox": {
      "min_lon": 4.374678764444366,
      "min_lat": 51.888764515698966,
      "max_lon": 4.374787911784299,
      "max_lat": 51.88882523761877
    },
    "center": {
      "lon": 4.374733338078988,
      "lat": 51.88879487666474
    }
  },
  {
    "file": "SN6_Train_AOI_11_Rotterdam_PS-RGB_20190804111224_20190804111453_tile_8689.tif",
    "label": "storagetank",
    "score": 0.71,
    "bbox": {
      "min_lon": 4.374180299257698,
      "min_lat": 51.889287266867086,
      "max_lon": 4.374294760555713,
      "max_lat": 51.889356203046574
    },
    "center": {
      "lon": 4.374237529864651,
      "lat": 51.8893217349645
    }
  },
  {
    "file": "SN6_Train_AOI_11_Rotterdam_PS-RGB_20190804111224_20190804111453_tile_8689.tif",
    "label": "storagetank",
    "score": 0.7,
    "bbox": {
      "min_lon": 4.375386608152981,
      "min_lat": 51.88863979560028,
      "max_lon": 4.375475074822696,
      "max_lat": 51.88869110430994
    },
    "center": {
      "lon": 4.3754308414636345,
      "lat": 51.88866544995932
    }
  },
  {
    "file": "SN6_Train_AOI_11_Rotterdam_PS-RGB_20190804111224_20190804111453_tile_8689.tif",
    "label": "storagetank",
    "score": 0.69,
    "bbox": {
      "min_lon": 4.375443937922716,
      "min_lat": 51.88848113074067,
      "max_lon": 4.375532505220712,
      "max_lat": 51.88853291333696
    },
    "center": {
      "lon": 4.375488221547264,
      "lat": 51.88850702204312
    }
  },
  {
    "file": "SN6_Train_AOI_11_Rotterdam_PS-RGB_20190804111224_20190804111453_tile_8689.tif",
    "label": "storagetank",
    "score": 0.69,
    "bbox": {
      "min_lon": 4.374629357493728,
      "min_lat": 51.88865264414433,
      "max_lon": 4.374742223822529,
      "max_lat": 51.88871579810768
    },
    "center": {
      "lon": 4.374685790620114,
      "lat": 51.88868422113236
    }
  },
  {
    "file": "SN6_Train_AOI_11_Rotterdam_PS-RGB_20190804111224_20190804111453_tile_8689.tif",
    "label": "storagetank",
    "score": 0.67,
    "bbox": {
      "min_lon": 4.375469205949896,
      "min_lat": 51.88854463113225,
      "max_lon": 4.375562431170653,
      "max_lat": 51.88859741065481
    },
    "center": {
      "lon": 4.375515818534036,
      "lat": 51.88857102089797
    }
  },
  {
    "file": "SN6_Train_AOI_11_Rotterdam_PS-RGB_20190804111224_20190804111453_tile_8689.tif",
    "label": "vehicle",
    "score": 0.66,
    "bbox": {
      "min_lon": 4.378670837568502,
      "min_lat": 51.88847600234728,
      "max_lon": 4.378756653115501,
      "max_lat": 51.888564804272384
    },
    "center": {
      "lon": 4.378713745301862,
      "lat": 51.88852040332333
    }
  },
  {
    "file": "SN6_Train_AOI_11_Rotterdam_PS-RGB_20190804111224_20190804111453_tile_8689.tif",
    "label": "storagetank",
    "score": 0.63,
    "bbox": {
      "min_lon": 4.374873322020622,
      "min_lat": 51.888729232214324,
      "max_lon": 4.374986400949022,
      "max_lat": 51.888793262372
    },
    "center": {
      "lon": 4.3749298614462155,
      "lat": 51.88876124729971
    }
  },
  {
    "file": "SN6_Train_AOI_11_Rotterdam_PS-RGB_20190804111224_20190804111453_tile_8689.tif",
    "label": "vehicle",
    "score": 0.63,
    "bbox": {
      "min_lon": 4.378597913133247,
      "min_lat": 51.890503533121915,
      "max_lon": 4.378663075942987,
      "max_lat": 51.89057231655903
    },
    "center": {
      "lon": 4.378630494514524,
      "lat": 51.89053792484858
    }
  },
  {
    "file": "SN6_Train_AOI_11_Rotterdam_PS-RGB_20190804111224_20190804111453_tile_8689.tif",
    "label": "storagetank",
    "score": 0.62,
    "bbox": {
      "min_lon": 4.3753405995566865,
      "min_lat": 51.88856361488399,
      "max_lon": 4.375433419443579,
      "max_lat": 51.88861789744504
    },
    "center": {
      "lon": 4.375387009473272,
      "lat": 51.88859075616924
    }
  },
  {
    "file": "SN6_Train_AOI_11_Rotterdam_PS-RGB_20190804111224_20190804111453_tile_8689.tif",
    "label": "storagetank",
    "score": 0.56,
    "bbox": {
      "min_lon": 4.374939716056714,
      "min_lat": 51.8886593453228,
      "max_lon": 4.375055456633305,
      "max_lat": 51.88872673931059
    },
    "center": {
      "lon": 4.374997586303424,
      "lat": 51.888693042323986
    }
  },
  {
    "file": "SN6_Train_AOI_11_Rotterdam_PS-RGB_20190804111224_20190804111453_tile_8689.tif",
    "label": "storagetank",
    "score": 0.56,
    "bbox": {
      "min_lon": 4.374495977839513,
      "min_lat": 51.88879362606984,
      "max_lon": 4.374608271920427,
      "max_lat": 51.888857321230525
    },
    "center": {
      "lon": 4.37455212484183,
      "lat": 51.88882547365666
    }
  },
  {
    "file": "SN6_Train_AOI_11_Rotterdam_PS-RGB_20190804111224_20190804111453_tile_8689.tif",
    "label": "storagetank",
    "score": 0.54,
    "bbox": {
      "min_lon": 4.377074969389963,
      "min_lat": 51.88835089896429,
      "max_lon": 4.377189918043317,
      "max_lat": 51.8884165505386
    },
    "center": {
      "lon": 4.3771324436764045,
      "lat": 51.88838372475834
    }
  },
  {
    "file": "SN6_Train_AOI_11_Rotterdam_PS-RGB_20190804111224_20190804111453_tile_8689.tif",
    "label": "storagetank",
    "score": 0.51,
    "bbox": {
      "min_lon": 4.374240932114489,
      "min_lat": 51.88861630633579,
      "max_lon": 4.37437438504509,
      "max_lat": 51.88869937613103
    },
    "center": {
      "lon": 4.3743076585207215,
      "lat": 51.88865784124459
    }
  },
  {
    "file": "SN6_Train_AOI_11_Rotterdam_PS-RGB_20190804111224_20190804111453_tile_8689.tif",
    "label": "storagetank",
    "score": 0.51,
    "bbox": {
      "min_lon": 4.374507523896666,
      "min_lat": 51.888612492991264,
      "max_lon": 4.374621431843978,
      "max_lat": 51.88868018496729
    },
    "center": {
      "lon": 4.37456447782922,
      "lat": 51.88864633898666
    }
  },
  {
    "file": "SN6_Train_AOI_11_Rotterdam_PS-RGB_20190804111224_20190804111453_tile_8689.tif",
    "label": "storagetank",
    "score": 0.5,
    "bbox": {
      "min_lon": 4.374692116910909,
      "min_lat": 51.88872049869579,
      "max_lon": 4.374769525979078,
      "max_lat": 51.888764948154446
    },
    "center": {
      "lon": 4.374730821426647,
      "lat": 51.88874272342828
    }
  },
  {
    "file": "SN6_Train_AOI_11_Rotterdam_PS-RGB_20190804111224_20190804111453_tile_8689.tif",
    "label": "storagetank",
    "score": 0.49,
    "bbox": {
      "min_lon": 4.375329166965133,
      "min_lat": 51.88848838518016,
      "max_lon": 4.375421899642621,
      "max_lat": 51.88854678395612
    },
    "center": {
      "lon": 4.3753755332750295,
      "lat": 51.888517584573684
    }
  },
  {
    "file": "SN6_Train_AOI_11_Rotterdam_PS-RGB_20190804111224_20190804111453_tile_8689.tif",
    "label": "storagetank",
    "score": 0.47,
    "bbox": {
      "min_lon": 4.374757432127557,
      "min_lat": 51.888691453160895,
      "max_lon": 4.374866914986997,
      "max_lat": 51.888754386725545
    },
    "center": {
      "lon": 4.37481217352054,
      "lat": 51.888722919949565
    }
  },
  {
    "file": "SN6_Train_AOI_11_Rotterdam_PS-RGB_20190804111224_20190804111453_tile_8689.tif",
    "label": "storagetank",
    "score": 0.46,
    "bbox": {
      "min_lon": 4.374566613764691,
      "min_lat": 51.88872295042671,
      "max_lon": 4.374675348489312,
      "max_lat": 51.88878820626894
    },
    "center": {
      "lon": 4.374620981089181,
      "lat": 51.88875557835468
    }
  },
  {
    "file": "SN6_Train_AOI_11_Rotterdam_PS-RGB_20190804111224_20190804111453_tile_8689.tif",
    "label": "storagetank",
    "score": 0.45,
    "bbox": {
      "min_lon": 4.374703974299134,
      "min_lat": 51.888572516806256,
      "max_lon": 4.37482939891987,
      "max_lat": 51.88864757660552
    },
    "center": {
      "lon": 4.374766686559324,
      "lat": 51.888610046714966
    }
  },
  {
    "file": "SN6_Train_AOI_11_Rotterdam_PS-RGB_20190804111224_20190804111453_tile_8689.tif",
    "label": "storagetank",
    "score": 0.44,
    "bbox": {
      "min_lon": 4.374442936818376,
      "min_lat": 51.888682052499384,
      "max_lon": 4.374560284036589,
      "max_lat": 51.88875166785957
    },
    "center": {
      "lon": 4.374501610383936,
      "lat": 51.88871686018727
    }
  },
  {
    "file": "SN6_Train_AOI_11_Rotterdam_PS-RGB_20190804111224_20190804111453_tile_8689.tif",
    "label": "storagetank",
    "score": 0.43,
    "bbox": {
      "min_lon": 4.375840890675968,
      "min_lat": 51.890529207696474,
      "max_lon": 4.37593031537951,
      "max_lat": 51.8905833058312
    },
    "center": {
      "lon": 4.375885603001955,
      "lat": 51.89055625676856
    }
  },
  {
    "file": "SN6_Train_AOI_11_Rotterdam_PS-RGB_20190804111224_20190804111453_tile_8689.tif",
    "label": "storagetank",
    "score": 0.42,
    "bbox": {
      "min_lon": 4.374311179170351,
      "min_lat": 51.88872387299949,
      "max_lon": 4.374400781433852,
      "max_lat": 51.888775477677626
    },
    "center": {
      "lon": 4.374355980277449,
      "lat": 51.88874967534284
    }
  },
  {
    "file": "SN6_Train_AOI_11_Rotterdam_PS-RGB_20190804111224_20190804111453_tile_8693.tif",
    "label": "vehicle",
    "score": 0.58,
    "bbox": {
      "min_lon": 4.3890337709212845,
      "min_lat": 51.8878115106872,
      "max_lon": 4.389161308326254,
      "max_lat": 51.88785442958322
    },
    "center": {
      "lon": 4.389097539594655,
      "lat": 51.887832970137836
    }
  },
  {
    "file": "SN6_Train_AOI_11_Rotterdam_PS-RGB_20190804111224_20190804111453_tile_8693.tif",
    "label": "vehicle",
    "score": 0.53,
    "bbox": {
      "min_lon": 4.3880000096476515,
      "min_lat": 51.888230774613405,
      "max_lon": 4.388057424064182,
      "max_lat": 51.888278672818586
    },
    "center": {
      "lon": 4.388028716841344,
      "lat": 51.88825472371984
    }
  },
  {
    "file": "SN6_Train_AOI_11_Rotterdam_PS-RGB_20190804111224_20190804111453_tile_8693.tif",
    "label": "vehicle",
    "score": 0.46,
    "bbox": {
      "min_lon": 4.393474088846394,
      "min_lat": 51.889572334334225,
      "max_lon": 4.3935588723546815,
      "max_lat": 51.88961225894746
    },
    "center": {
      "lon": 4.393516480582487,
      "lat": 51.8895922966433
    }
  },
  {
    "file": "SN6_Train_AOI_11_Rotterdam_PS-RGB_20190804111224_20190804111453_tile_8693.tif",
    "label": "vehicle",
    "score": 0.46,
    "bbox": {
      "min_lon": 4.3936655059151715,
      "min_lat": 51.88953575846464,
      "max_lon": 4.393735521939874,
      "max_lat": 51.8895665698113
    },
    "center": {
      "lon": 4.39370051391602,
      "lat": 51.88955116413942
    }
  },
  {
    "file": "SN6_Train_AOI_11_Rotterdam_PS-RGB_20190804111224_20190804111453_tile_8693.tif",
    "label": "vehicle",
    "score": 0.42,
    "bbox": {
      "min_lon": 4.389465779859953,
      "min_lat": 51.88767867247221,
      "max_lon": 4.389520141424739,
      "max_lat": 51.88773372932303
    },
    "center": {
      "lon": 4.389492960626576,
      "lat": 51.887706200902784
    }
  },
  {
    "file": "SN6_Train_AOI_11_Rotterdam_PS-RGB_20190804111224_20190804111453_tile_8693.tif",
    "label": "vehicle",
    "score": 0.42,
    "bbox": {
      "min_lon": 4.391428904238582,
      "min_lat": 51.887792731696905,
      "max_lon": 4.391495738995995,
      "max_lat": 51.887817154675844
    },
    "center": {
      "lon": 4.391462321608596,
      "lat": 51.88780494318724
    }
  },
  {
    "file": "SN6_Train_AOI_11_Rotterdam_PS-RGB_20190804111224_20190804111453_tile_8695.tif",
    "label": "vehicle",
    "score": 0.54,
    "bbox": {
      "min_lon": 4.3979570821278315,
      "min_lat": 51.88753062638597,
      "max_lon": 4.398157139668671,
      "max_lat": 51.88762439034327
    },
    "center": {
      "lon": 4.398057110798238,
      "lat": 51.887577508378165
    }
  },
  {
    "file": "SN6_Train_AOI_11_Rotterdam_PS-RGB_20190804111224_20190804111453_tile_8695.tif",
    "label": "vehicle",
    "score": 0.51,
    "bbox": {
      "min_lon": 4.39786240194935,
      "min_lat": 51.88765679475222,
      "max_lon": 4.398051316011466,
      "max_lat": 51.887739553731
    },
    "center": {
      "lon": 4.39795685889706,
      "lat": 51.887698174252016
    }
  },
  {
    "file": "SN6_Train_AOI_11_Rotterdam_PS-RGB_20190804111224_20190804111453_tile_8695.tif",
    "label": "chimney",
    "score": 0.46,
    "bbox": {
      "min_lon": 4.3973053877349235,
      "min_lat": 51.889868357378475,
      "max_lon": 4.397812140695156,
      "max_lat": 51.89014552702936
    },
    "center": {
      "lon": 4.397558763466367,
      "lat": 51.890006942325655
    }
  },
  {
    "file": "SN6_Train_AOI_11_Rotterdam_PS-RGB_20190804111224_20190804111453_tile_8695.tif",
    "label": "Expressway-Service-area",
    "score": 0.44,
    "bbox": {
      "min_lon": 4.396939271084365,
      "min_lat": 51.887250063303874,
      "max_lon": 4.398665540621465,
      "max_lat": 51.8882410209946
    },
    "center": {
      "lon": 4.397802396738258,
      "lat": 51.88774554371736
    }
  },
  {
    "file": "SN6_Train_AOI_11_Rotterdam_PS-RGB_20190804111851_20190804112030_tile_5176.tif",
    "label": "vehicle",
    "score": 0.55,
    "bbox": {
      "min_lon": 4.397808059723134,
      "min_lat": 51.85989697947096,
      "max_lon": 4.397900160714733,
      "max_lat": 51.85992598161343
    },
    "center": {
      "lon": 4.397854110204755,
      "lat": 51.85991148054337
    }
  },
  {
    "file": "SN6_Train_AOI_11_Rotterdam_PS-RGB_20190804113009_20190804113242_tile_4797.tif",
    "label": "storagetank",
    "score": 0.59,
    "bbox": {
      "min_lon": 4.346934183731313,
      "min_lat": 51.89366234063703,
      "max_lon": 4.347162009555361,
      "max_lat": 51.893795009734845
    },
    "center": {
      "lon": 4.3470480964820375,
      "lat": 51.89372867521428
    }
  },
  {
    "file": "SN6_Train_AOI_11_Rotterdam_PS-RGB_20190804113009_20190804113242_tile_4797.tif",
    "label": "storagetank",
    "score": 0.49,
    "bbox": {
      "min_lon": 4.347240613418729,
      "min_lat": 51.89376582918872,
      "max_lon": 4.3473807295004345,
      "max_lat": 51.89384430270785
    },
    "center": {
      "lon": 4.347310671400888,
      "lat": 51.89380506595813
    }
  },
  {
    "file": "SN6_Train_AOI_11_Rotterdam_PS-RGB_20190804113009_20190804113242_tile_4798.tif",
    "label": "storagetank",
    "score": 0.96,
    "bbox": {
      "min_lon": 4.341316456719975,
      "min_lat": 51.890872764990974,
      "max_lon": 4.341600681425599,
      "max_lat": 51.8910423382806
    },
    "center": {
      "lon": 4.341458568815614,
      "lat": 51.89095755168225
    }
  },
  {
    "file": "SN6_Train_AOI_11_Rotterdam_PS-RGB_20190804113009_20190804113242_tile_4798.tif",
    "label": "ship",
    "score": 0.95,
    "bbox": {
      "min_lon": 4.341615886661122,
      "min_lat": 51.89088583511769,
      "max_lon": 4.344094072548332,
      "max_lat": 51.892068326116224
    },
    "center": {
      "lon": 4.342854963953601,
      "lat": 51.8914770827952
    }
  },
  {
    "file": "SN6_Train_AOI_11_Rotterdam_PS-RGB_20190804113009_20190804113242_tile_4798.tif",
    "label": "storagetank",
    "score": 0.94,
    "bbox": {
      "min_lon": 4.347092238274828,
      "min_lat": 51.89184059827349,
      "max_lon": 4.3474931889932105,
      "max_lat": 51.892091450001296
    },
    "center": {
      "lon": 4.347292713097668,
      "lat": 51.891966024239714
    }
  },
  {
    "file": "SN6_Train_AOI_11_Rotterdam_PS-RGB_20190804113009_20190804113242_tile_4798.tif",
    "label": "storagetank",
    "score": 0.88,
    "bbox": {
      "min_lon": 4.347222540322178,
      "min_lat": 51.89129130776609,
      "max_lon": 4.3475212776933505,
      "max_lat": 51.89148880627769
    },
    "center": {
      "lon": 4.347371908693352,
      "lat": 51.89139005708578
    }
  },
  {
    "file": "SN6_Train_AOI_11_Rotterdam_PS-RGB_20190804113009_20190804113242_tile_4798.tif",
    "label": "storagetank",
    "score": 0.78,
    "bbox": {
      "min_lon": 4.341591753154577,
      "min_lat": 51.89082478264467,
      "max_lon": 4.341787228916155,
      "max_lat": 51.89093856217037
    },
    "center": {
      "lon": 4.341689490916669,
      "lat": 51.89088167242837
    }
  },
  {
    "file": "SN6_Train_AOI_11_Rotterdam_PS-RGB_20190804113009_20190804113242_tile_4798.tif",
    "label": "storagetank",
    "score": 0.78,
    "bbox": {
      "min_lon": 4.34712682645515,
      "min_lat": 51.89091321150998,
      "max_lon": 4.347260416441841,
      "max_lat": 51.890985729017814
    },
    "center": {
      "lon": 4.347193621396781,
      "lat": 51.890949470272275
    }
  },
  {
    "file": "SN6_Train_AOI_11_Rotterdam_PS-RGB_20190804113009_20190804113242_tile_4798.tif",
    "label": "storagetank",
    "score": 0.7,
    "bbox": {
      "min_lon": 4.341765251324465,
      "min_lat": 51.890770653406676,
      "max_lon": 4.341927035938223,
      "max_lat": 51.89086674587542
    },
    "center": {
      "lon": 4.34184614354839,
      "lat": 51.890818699655966
    }
  },
  {
    "file": "SN6_Train_AOI_11_Rotterdam_PS-RGB_20190804113009_20190804113242_tile_4798.tif",
    "label": "ship",
    "score": 0.62,
    "bbox": {
      "min_lon": 4.343622579534544,
      "min_lat": 51.89128783846801,
      "max_lon": 4.34470050623415,
      "max_lat": 51.892175484732505
    },
    "center": {
      "lon": 4.344161537804793,
      "lat": 51.891731662924165
    }
  },
  {
    "file": "SN6_Train_AOI_11_Rotterdam_PS-RGB_20190804113009_20190804113242_tile_4798.tif",
    "label": "storagetank",
    "score": 0.61,
    "bbox": {
      "min_lon": 4.341167733268848,
      "min_lat": 51.890757703084894,
      "max_lon": 4.3414044435409584,
      "max_lat": 51.890893535996014
    },
    "center": {
      "lon": 4.341286088233287,
      "lat": 51.89082561957011
    }
  },
  {
    "file": "SN6_Train_AOI_11_Rotterdam_PS-RGB_20190804113009_20190804113242_tile_4798.tif",
    "label": "storagetank",
    "score": 0.59,
    "bbox": {
      "min_lon": 4.34710819643128,
      "min_lat": 51.89098451984193,
      "max_lon": 4.347211380548564,
      "max_lat": 51.891043899911494
    },
    "center": {
      "lon": 4.347159788457223,
      "lat": 51.89101420988237
    }
  },
  {
    "file": "SN6_Train_AOI_11_Rotterdam_PS-RGB_20190804113009_20190804113242_tile_4798.tif",
    "label": "storagetank",
    "score": 0.58,
    "bbox": {
      "min_lon": 4.347112600349226,
      "min_lat": 51.89104996972605,
      "max_lon": 4.347193857255019,
      "max_lat": 51.89109358116366
    },
    "center": {
      "lon": 4.347153228783207,
      "lat": 51.89107177544789
    }
  },
  {
    "file": "SN6_Train_AOI_11_Rotterdam_PS-RGB_20190804113009_20190804113242_tile_4798.tif",
    "label": "storagetank",
    "score": 0.56,
    "bbox": {
      "min_lon": 4.341110287073843,
      "min_lat": 51.89097770438016,
      "max_lon": 4.3413729388670514,
      "max_lat": 51.8911449074553
    },
    "center": {
      "lon": 4.341241612736271,
      "lat": 51.89106130596332
    }
  },
  {
    "file": "SN6_Train_AOI_11_Rotterdam_PS-RGB_20190804113009_20190804113242_tile_4799.tif",
    "label": "storagetank",
    "score": 0.87,
    "bbox": {
      "min_lon": 4.348308190155135,
      "min_lat": 51.8934539231444,
      "max_lon": 4.348532099929072,
      "max_lat": 51.89357875996424
    },
    "center": {
      "lon": 4.348420144892895,
      "lat": 51.89351634157922
    }
  },
  {
    "file": "SN6_Train_AOI_11_Rotterdam_PS-RGB_20190804113009_20190804113242_tile_4799.tif",
    "label": "storagetank",
    "score": 0.79,
    "bbox": {
      "min_lon": 4.347733230949716,
      "min_lat": 51.893503199822234,
      "max_lon": 4.348072360859895,
      "max_lat": 51.893705929930235
    },
    "center": {
      "lon": 4.3479027955379985,
      "lat": 51.893604564942635
    }
  },
  {
    "file": "SN6_Train_AOI_11_Rotterdam_PS-RGB_20190804113009_20190804113242_tile_4799.tif",
    "label": "storagetank",
    "score": 0.76,
    "bbox": {
      "min_lon": 4.348270240753633,
      "min_lat": 51.89359944227739,
      "max_lon": 4.348492721947445,
      "max_lat": 51.893717780752795
    },
    "center": {
      "lon": 4.348381481209963,
      "lat": 51.89365861153729
    }
  },
  {
    "file": "SN6_Train_AOI_11_Rotterdam_PS-RGB_20190804113009_20190804113242_tile_4799.tif",
    "label": "storagetank",
    "score": 0.7,
    "bbox": {
      "min_lon": 4.347895145358459,
      "min_lat": 51.893908581544636,
      "max_lon": 4.348138666707583,
      "max_lat": 51.894050934308495
    },
    "center": {
      "lon": 4.348016905848034,
      "lat": 51.8939797579592
    }
  },
  {
    "file": "SN6_Train_AOI_11_Rotterdam_PS-RGB_20190804113009_20190804113242_tile_4799.tif",
    "label": "storagetank",
    "score": 0.6,
    "bbox": {
      "min_lon": 4.348128410523314,
      "min_lat": 51.893946183320445,
      "max_lon": 4.348350237246268,
      "max_lat": 51.894069401639825
    },
    "center": {
      "lon": 4.3482393237388814,
      "lat": 51.8940077925044
    }
  },
  {
    "file": "SN6_Train_AOI_11_Rotterdam_PS-RGB_20190804113009_20190804113242_tile_4799.tif",
    "label": "storagetank",
    "score": 0.56,
    "bbox": {
      "min_lon": 4.348449938299411,
      "min_lat": 51.89336932644007,
      "max_lon": 4.348539493091048,
      "max_lat": 51.893421920018994
    },
    "center": {
      "lon": 4.348494715670099,
      "lat": 51.89339562323399
    }
  },
  {
    "file": "SN6_Train_AOI_11_Rotterdam_PS-RGB_20190804113009_20190804113242_tile_4799.tif",
    "label": "ship",
    "score": 0.55,
    "bbox": {
      "min_lon": 4.349331438151395,
      "min_lat": 51.89515593377929,
      "max_lon": 4.349742137502514,
      "max_lat": 51.895323413035726
    },
    "center": {
      "lon": 4.349536787459794,
      "lat": 51.895239673449794
    }
  },
  {
    "file": "SN6_Train_AOI_11_Rotterdam_PS-RGB_20190804113009_20190804113242_tile_4799.tif",
    "label": "vehicle",
    "score": 0.51,
    "bbox": {
      "min_lon": 4.349816142056274,
      "min_lat": 51.89315376998539,
      "max_lon": 4.349925025563701,
      "max_lat": 51.89331469932121
    },
    "center": {
      "lon": 4.349870583719042,
      "lat": 51.893234234698774
    }
  },
  {
    "file": "SN6_Train_AOI_11_Rotterdam_PS-RGB_20190804113009_20190804113242_tile_4799.tif",
    "label": "vehicle",
    "score": 0.5,
    "bbox": {
      "min_lon": 4.349706007238291,
      "min_lat": 51.89316490659878,
      "max_lon": 4.349788303647191,
      "max_lat": 51.8932991884101
    },
    "center": {
      "lon": 4.3497471553857245,
      "lat": 51.893232047536266
    }
  },
  {
    "file": "SN6_Train_AOI_11_Rotterdam_PS-RGB_20190804113009_20190804113242_tile_4799.tif",
    "label": "vehicle",
    "score": 0.47,
    "bbox": {
      "min_lon": 4.352633156800938,
      "min_lat": 51.89389973437874,
      "max_lon": 4.352696938250882,
      "max_lat": 51.893957715262346
    },
    "center": {
      "lon": 4.352665047506331,
      "lat": 51.893928724826246
    }
  },
  {
    "file": "SN6_Train_AOI_11_Rotterdam_PS-RGB_20190804113009_20190804113242_tile_4799.tif",
    "label": "vehicle",
    "score": 0.46,
    "bbox": {
      "min_lon": 4.349720931814171,
      "min_lat": 51.893064400138215,
      "max_lon": 4.349818920986096,
      "max_lat": 51.893233053829015
    },
    "center": {
      "lon": 4.349769926315171,
      "lat": 51.89314872703396
    }
  },
  {
    "file": "SN6_Train_AOI_11_Rotterdam_PS-RGB_20190804113009_20190804113242_tile_4800.tif",
    "label": "storagetank",
    "score": 0.95,
    "bbox": {
      "min_lon": 4.347902594426066,
      "min_lat": 51.89133975713257,
      "max_lon": 4.348355422203128,
      "max_lat": 51.89158650849087
    },
    "center": {
      "lon": 4.3481290077181205,
      "lat": 51.891463132908704
    }
  },
  {
    "file": "SN6_Train_AOI_11_Rotterdam_PS-RGB_20190804113009_20190804113242_tile_4800.tif",
    "label": "storagetank",
    "score": 0.85,
    "bbox": {
      "min_lon": 4.347847225246159,
      "min_lat": 51.89098494540131,
      "max_lon": 4.348427010904562,
      "max_lat": 51.89128625871983
    },
    "center": {
      "lon": 4.348137117142603,
      "lat": 51.891135602204066
    }
  },
  {
    "file": "SN6_Train_AOI_11_Rotterdam_PS-RGB_20190804113009_20190804113242_tile_4800.tif",
    "label": "storagetank",
    "score": 0.74,
    "bbox": {
      "min_lon": 4.3475882527825345,
      "min_lat": 51.89098447796425,
      "max_lon": 4.34804082019559,
      "max_lat": 51.89125518233658
    },
    "center": {
      "lon": 4.34781453583549,
      "lat": 51.891119830268806
    }
  },
  {
    "file": "SN6_Train_AOI_11_Rotterdam_PS-RGB_20190804113009_20190804113242_tile_4800.tif",
    "label": "chimney",
    "score": 0.6,
    "bbox": {
      "min_lon": 4.347659253827655,
      "min_lat": 51.891619768989045,
      "max_lon": 4.348258207222432,
      "max_lat": 51.89201407853465
    },
    "center": {
      "lon": 4.347958729266411,
      "lat": 51.89181692401636
    }
  },
  {
    "file": "SN6_Train_AOI_11_Rotterdam_PS-RGB_20190804113009_20190804113242_tile_4800.tif",
    "label": "vehicle",
    "score": 0.54,
    "bbox": {
      "min_lon": 4.351043592628779,
      "min_lat": 51.89211205155714,
      "max_lon": 4.35126631066052,
      "max_lat": 51.892170509994585
    },
    "center": {
      "lon": 4.351154951575643,
      "lat": 51.89214128078039
    }
  },
  {
    "file": "SN6_Train_AOI_11_Rotterdam_PS-RGB_20190804113009_20190804113242_tile_4800.tif",
    "label": "chimney",
    "score": 0.47,
    "bbox": {
      "min_lon": 4.348386224593687,
      "min_lat": 51.89172937216478,
      "max_lon": 4.348976272870371,
      "max_lat": 51.892096061236046
    },
    "center": {
      "lon": 4.348681247578206,
      "lat": 51.891912716918824
    }
  },
  {
    "file": "SN6_Train_AOI_11_Rotterdam_PS-RGB_20190804113009_20190804113242_tile_4800.tif",
    "label": "vehicle",
    "score": 0.4,
    "bbox": {
      "min_lon": 4.3505001620319685,
      "min_lat": 51.89125012255647,
      "max_lon": 4.350617528660872,
      "max_lat": 51.89143717943269
    },
    "center": {
      "lon": 4.350558845232992,
      "lat": 51.89134365105625
    }
  }
]